[
  {
    "workload_uuid": "8b76699b-34e5-50cf-8474-2dad94d93203",
    "status": "passed",
    "axes": {
      "batch_size": 1,
      "seq_len": 4096
    },
    "axes_label": "batch_size=1,seq_len=4096",
    "t_sol_ms": 0.274877906944,
    "t_base_ms": 1.00765012105306,
    "mfu_pct": 27.279102259893023,
    "bw_util_pct": 2.3153751002002276,
    "t_base_over_t_sol": 3.665809785354431,
    "regime": "compute",
    "mfu_ceiling": 1.0,
    "cost_source": "ray234"
  },
  {
    "workload_uuid": "c41bb015-c8a3-58de-9766-63404b898941",
    "status": "passed",
    "axes": {
      "batch_size": 2,
      "seq_len": 128
    },
    "axes_label": "batch_size=2,seq_len=128",
    "t_sol_ms": 0.011034688,
    "t_base_ms": 0.21038293838500977,
    "mfu_pct": 4.65008290986403,
    "bw_util_pct": 5.24504890211489,
    "t_base_over_t_sol": 19.06559917099693,
    "regime": "balanced",
    "mfu_ceiling": 0.8865661687137063,
    "cost_source": "ray234"
  },
  {
    "workload_uuid": "c66be57d-851b-52cb-9f39-1ee8c3de12db",
    "status": "passed",
    "axes": {
      "batch_size": 16,
      "seq_len": 256
    },
    "axes_label": "batch_size=16,seq_len=256",
    "t_sol_ms": 0.16034544571733333,
    "t_base_ms": 0.8039530436197916,
    "mfu_pct": 19.944628232935017,
    "bw_util_pct": 2.4129170421020403,
    "t_base_over_t_sol": 5.013881373575454,
    "regime": "compute",
    "mfu_ceiling": 1.0,
    "cost_source": "ray234"
  }
]
